lukhed_stocks/__init__.py
lukhed_stocks/cat.py
lukhed_stocks/marketdata.py
lukhed_stocks/polygon.py
lukhed_stocks/robinhood.py
lukhed_stocks/schwab.py
lukhed_stocks/tickers.py
lukhed_stocks/tradingview.py
lukhed_stocks/webull.py
lukhed_stocks/wikipedia.py
tests/__init__.py
tests/test_tickers.py
lukhed_stocks-0.3.0.dist-info/LICENSE
lukhed_stocks-0.3.0.dist-info/METADATA
lukhed_stocks-0.3.0.dist-info/WHEEL
lukhed_stocks-0.3.0.dist-info/top_level.txt
lukhed_stocks-0.3.0.dist-info/RECORD
