Metadata-Version: 2.1
Name: lukhed-stocks
Version: 0.3.0
Summary: A collection of stock analysis functions and api wrappers
Home-page: https://github.com/lukhed/lukhed_stocks
Author: lukhed
Author-email: lukhed.mail@gmail.com
Classifier: Programming Language :: Python :: 3
Classifier: License :: OSI Approved :: MIT License
Classifier: Operating System :: OS Independent
Requires-Python: >=3.10
License-File: LICENSE
Requires-Dist: lukhed-basic-utils>=1.6.6
Requires-Dist: schwab-py>=1.4.0
